snips_nlu_rust/__init__.py
snips_nlu_rust/__version__
snips_nlu_rust/nlu_engine.py
snips_nlu_rust/utils.py
snips_nlu_rust/dylib/.gitignore
snips_nlu_rust/dylib/libsnips_nlu_rs.so
snips_nlu_rust-0.57.0.dist-info/METADATA
snips_nlu_rust-0.57.0.dist-info/RECORD
snips_nlu_rust-0.57.0.dist-info/WHEEL
snips_nlu_rust-0.57.0.dist-info/top_level.txt
