Metadata-Version: 1.1
Name: snips_nlu_rust
Version: 0.57.0
Summary: Python wrapper of the Snips NLU engine
Home-page: UNKNOWN
Author: Thibaut Lorrain, Adrien Ball
Author-email: thibaut.lorrain@snips.ai, adrien.ball@snips.ai
License: UNKNOWN
Platform: UNKNOWN
Classifier: Programming Language :: Python :: 2
Classifier: Programming Language :: Python :: 2.7
Classifier: Programming Language :: Python :: 3
Classifier: Programming Language :: Python :: 3.4
Classifier: Programming Language :: Python :: 3.5
Classifier: Programming Language :: Python :: 3.6
